_zodbc.cpython-312-x86_64-linux-gnu.so
zodbc.py
zodbc.libs/libltdl-8551cbec.so.7.3.3
zodbc.libs/libodbc-cf61561c.so.2.0.0
zodbc-0.9.1.dist-info/METADATA
zodbc-0.9.1.dist-info/WHEEL
zodbc-0.9.1.dist-info/top_level.txt
zodbc-0.9.1.dist-info/RECORD
