Metadata-Version: 2.4
Name: zodbc
Version: 0.9.1
Summary: DBAPI2-like ODBC client with Apache Arrow support
Author: Felix Graßl
License-Expression: MIT
Project-URL: Homepage, https://github.com/ffelixg/zodbc_py
Keywords: odbc,arrow,mssql,sql server
Classifier: Programming Language :: Python
Classifier: Topic :: Database
Classifier: Intended Audience :: Developers
Requires-Python: >=3.10
Provides-Extra: pyarrow
Requires-Dist: pyarrow; extra == "pyarrow"
